imageSizeReducer/__init__.py
imageSizeReducer/imageSizeReducer.py
imageSizeReducer-0.2.1.dist-info/LICENSE
imageSizeReducer-0.2.1.dist-info/METADATA
imageSizeReducer-0.2.1.dist-info/WHEEL
imageSizeReducer-0.2.1.dist-info/top_level.txt
imageSizeReducer-0.2.1.dist-info/RECORD
