Metadata-Version: 2.1
Name: imageSizeReducer
Version: 0.2.1
Summary: Reduce image size
Home-page: https://github.com/devdp/image-resizer.git
Author: Bramhesh Kumar Srivastava
Author-email: brahmesh1996@gmail.com
License: MIT
Platform: UNKNOWN
Classifier: Programming Language :: Python :: 3.5
Classifier: Programming Language :: Python :: 3.6
Classifier: Programming Language :: Python :: 3.7
Classifier: Programming Language :: Python :: 3.8
Classifier: Programming Language :: Python :: 3.9
Requires-Dist: pillow
Requires-Dist: python-math
